crewai_tools_cn/__init__.py
crewai_tools_cn/adapters/embedchain_adapter.py
crewai_tools_cn/adapters/lancedb_adapter.py
crewai_tools_cn/adapters/pdf_embedchain_adapter.py
crewai_tools_cn/tools/__init__.py
crewai_tools_cn/tools/base_tool.py
crewai_tools_cn/tools/browserbase_load_tool/README.md
crewai_tools_cn/tools/browserbase_load_tool/browserbase_load_tool.py
crewai_tools_cn/tools/code_docs_search_tool/README.md
crewai_tools_cn/tools/code_docs_search_tool/code_docs_search_tool.py
crewai_tools_cn/tools/code_interpreter_tool/Dockerfile
crewai_tools_cn/tools/code_interpreter_tool/README.md
crewai_tools_cn/tools/code_interpreter_tool/code_interpreter_tool.py
crewai_tools_cn/tools/composio_tool/README.md
crewai_tools_cn/tools/composio_tool/composio_tool.py
crewai_tools_cn/tools/csv_search_tool/README.md
crewai_tools_cn/tools/csv_search_tool/csv_search_tool.py
crewai_tools_cn/tools/directory_read_tool/README.md
crewai_tools_cn/tools/directory_read_tool/directory_read_tool.py
crewai_tools_cn/tools/directory_search_tool/README.md
crewai_tools_cn/tools/directory_search_tool/directory_search_tool.py
crewai_tools_cn/tools/docx_search_tool/README.md
crewai_tools_cn/tools/docx_search_tool/docx_search_tool.py
crewai_tools_cn/tools/exa_tools/README.md
crewai_tools_cn/tools/exa_tools/exa_base_tool.py
crewai_tools_cn/tools/exa_tools/exa_search_tool.py
crewai_tools_cn/tools/file_read_tool/README.md
crewai_tools_cn/tools/file_read_tool/file_read_tool.py
crewai_tools_cn/tools/firecrawl_crawl_website_tool/README.md
crewai_tools_cn/tools/firecrawl_crawl_website_tool/firecrawl_crawl_website_tool.py
crewai_tools_cn/tools/firecrawl_scrape_website_tool/README.md
crewai_tools_cn/tools/firecrawl_scrape_website_tool/firecrawl_scrape_website_tool.py
crewai_tools_cn/tools/firecrawl_search_tool/README.md
crewai_tools_cn/tools/firecrawl_search_tool/firecrawl_search_tool.py
crewai_tools_cn/tools/github_search_tool/README.md
crewai_tools_cn/tools/github_search_tool/github_search_tool.py
crewai_tools_cn-0.4.26.dist-info/LICENSE
crewai_tools_cn-0.4.26.dist-info/LICENSE-MIT.md
crewai_tools_cn-0.4.26.dist-info/METADATA
crewai_tools_cn-0.4.26.dist-info/WHEEL
crewai_tools_cn-0.4.26.dist-info/RECORD
