Metadata-Version: 2.1
Name: crewai-tools-cn
Version: 0.4.26
Summary: Set of tools for the crewAI framework (Chinese Version)
Author: AiPMHub
Author-email: nextprofessionalpower@gmail.com
Requires-Python: >=3.10,<=3.13
Classifier: Programming Language :: Python :: 3
Classifier: Programming Language :: Python :: 3.10
Classifier: Programming Language :: Python :: 3.11
Classifier: Programming Language :: Python :: 3.12
Requires-Dist: beautifulsoup4 (>=4.12.3,<5.0.0)
Requires-Dist: chromadb (>=0.4.22,<0.5.0)
Requires-Dist: docker (>=7.1.0,<8.0.0)
Requires-Dist: docx2txt (>=0.8,<0.9)
Requires-Dist: embedchain (>=0.1.114,<0.2.0)
Requires-Dist: lancedb (>=0.5.4,<0.6.0)
Requires-Dist: langchain (>0.2,<=0.3)
Requires-Dist: openai (>=1.12.0,<2.0.0)
Requires-Dist: pydantic (>=2.6.1,<3.0.0)
Requires-Dist: pyright (>=1.1.350,<2.0.0)
Requires-Dist: pytest (>=8.0.0,<9.0.0)
Requires-Dist: pytube (>=15.0.0,<16.0.0)
Requires-Dist: requests (>=2.31.0,<3.0.0)
Requires-Dist: selenium (>=4.18.1,<5.0.0)
Project-URL: Homepage, https://crewai.com
Project-URL: Repository, https://github.com/aithoughts/aipmAI-tools
